irdap/__init__.py
irdap/__main__.py
irdap/config.conf
irdap/irdap.py
irdap/pca_adi.py
irdap/print_in_terminal.txt
irdap/version.py
irdap/static_calibs/master_badpix.fits
irdap/static_calibs/master_flat_H.fits
irdap/static_calibs/master_flat_J.fits
irdap/static_calibs/master_flat_Ks.fits
irdap/static_calibs/master_flat_Y.fits
irdap/static_calibs/transmission_SPHERE_CPI_ND.txt
irdap/static_calibs/transmission_SPHERE_IRDIS_BBF_H.txt
irdap/static_calibs/transmission_SPHERE_IRDIS_BBF_J.txt
irdap/static_calibs/transmission_SPHERE_IRDIS_BBF_Ks.txt
irdap/static_calibs/transmission_SPHERE_IRDIS_BBF_Y.txt
irdap/static_calibs/transmission_SPHERE_IRDIS_NBF_BrG.txt
irdap/static_calibs/transmission_SPHERE_IRDIS_NBF_CO.txt
irdap/static_calibs/transmission_SPHERE_IRDIS_NBF_CntK2.txt
irdap/static_calibs/transmission_SPHERE_IRDIS_NBF_ContH.txt
irdap/static_calibs/transmission_SPHERE_IRDIS_NBF_ContJ.txt
irdap/static_calibs/transmission_SPHERE_IRDIS_NBF_ContK1.txt
irdap/static_calibs/transmission_SPHERE_IRDIS_NBF_FeII.txt
irdap/static_calibs/transmission_SPHERE_IRDIS_NBF_H2.txt
irdap/static_calibs/transmission_SPHERE_IRDIS_NBF_HeI.txt
irdap/static_calibs/transmission_SPHERE_IRDIS_NBF_PaB.txt
irdap-1.3.5.dist-info/LICENSE
irdap-1.3.5.dist-info/METADATA
irdap-1.3.5.dist-info/WHEEL
irdap-1.3.5.dist-info/entry_points.txt
irdap-1.3.5.dist-info/top_level.txt
irdap-1.3.5.dist-info/RECORD
