Metadata-Version: 2.1
Name: irdap
Version: 1.3.5
Summary: IRDAP is a highly-automated end-to-end pipeline to reduce SPHERE-IRDIS polarimetric data
Home-page: https://irdap.readthedocs.io
Download-URL: https://github.com/robvanholstein/IRDAP/archive/master.zip
Author: R.G. van Holstein
Author-email: rob.vanholstein@eso.org
License: GNU General Public License v3.0
Classifier: Development Status :: 3 - Alpha
Classifier: Intended Audience :: Science/Research
Classifier: Topic :: Scientific/Engineering :: Astronomy
Classifier: License :: OSI Approved :: GNU General Public License v3 (GPLv3)
Classifier: Programming Language :: Python :: 3.6
Classifier: Programming Language :: Python :: 3.7
Requires-Python: >=3
License-File: LICENSE
Requires-Dist: numpy (>=1.16.1)
Requires-Dist: matplotlib (>=3.0.1)
Requires-Dist: scipy (>=1.2.1)
Requires-Dist: astropy (>=3.1.1)
Requires-Dist: scikit-image (>=0.19.2)
Requires-Dist: pandas (>=0.23.4)
Requires-Dist: photutils (>=0.7.1)
